utility.py
api/__init__.py
api/asgi.py
api/settings.py
api/urls.py
api/wsgi.py
api/mapper/__init__.py
api/mapper/admin.py
api/mapper/algo_functions.py
api/mapper/apps.py
api/mapper/models.py
api/mapper/serializers.py
api/mapper/suggestion_based_algo_functions.py
api/mapper/tests.py
api/mapper/views.py
api/mapper/algos/OAI_with_openai4.py
api/mapper/algos/__init__.py
api/mapper/algos/fuzzywuzzy.py
api/mapper/algos/fw_with_openai4.py
api/mapper/algos/fw_with_openai4_with_sample.py
api/mapper/algos/harmonization_with_suggestion_service.py
api/mapper/algos/jw_with_openai.py
api/mapper/algos/jw_with_openai4.py
api/mapper/algos/jw_with_openai4_with_sample.py
api/mapper/algos/jw_with_openai_with_sample.py
api/mapper/algos/oai_with_openai4_with_sample.py
api/mapper/algos/openai.py
api/mapper/algos/openaiGPT4.py
api/mapper/algos/openaiGPT4_with_sample.py
api/mapper/algos/openai_embedding.py
api/mapper/algos/openai_with_sample.py
api/mapper/algos/rapidfuzz.py
api/mapper/algos/recursive_harmonization.py
api/mapper/algos/stringmetric.py
api/mapper/algos/w2V_with_openai4.py
api/mapper/algos/w2v_with_openai4_with_sample.py
api/mapper/algos/word2vecEmbedding.py
dp_ai_data_harmonization-1.0.2.dist-info/METADATA
dp_ai_data_harmonization-1.0.2.dist-info/WHEEL
dp_ai_data_harmonization-1.0.2.dist-info/top_level.txt
dp_ai_data_harmonization-1.0.2.dist-info/RECORD
