Metadata-Version: 2.1
Name: dp-ai-data-harmonization
Version: 1.0.2
Summary: Create data quality rules and apply them to datasets.
Author: Himanshu
Author-email: himanshu.tomar@decisionpoint.in
Classifier: Programming Language :: Python :: 3
Classifier: License :: OSI Approved :: MIT License
Classifier: Operating System :: OS Independent
Requires-Python: >=3.8
Requires-Dist: openai
Requires-Dist: pandas
Requires-Dist: fuzzywuzzy
Requires-Dist: stringmetric
Requires-Dist: rapidfuzz
Requires-Dist: IPython
Requires-Dist: textdistance
Requires-Dist: django
